nam/__init__.py
nam/data_utils.py
nam/metrics.py
nam/model.py
nam_pt-0.3.dist-info/METADATA
nam_pt-0.3.dist-info/WHEEL
nam_pt-0.3.dist-info/top_level.txt
nam_pt-0.3.dist-info/RECORD
