Metadata-Version: 2.1
Name: nam-pt
Version: 0.3
Summary: Neural Additive Models (PyTorch): Intepretable ML with Neural Nets
Home-page: https://github.com/kherud/neural-additive-models-pt
Author: Konstantin Herud
License: Apache 2.0
Keywords: nam,interpretability,machine,learning,research
Platform: UNKNOWN
Classifier: Development Status :: 4 - Beta
Classifier: Intended Audience :: Developers
Classifier: Intended Audience :: Education
Classifier: Intended Audience :: Science/Research
Classifier: License :: OSI Approved :: Apache Software License
Classifier: Programming Language :: Python :: 3
Classifier: Programming Language :: Python :: 3.5
Classifier: Programming Language :: Python :: 3.6
Classifier: Programming Language :: Python :: 3.7
Classifier: Programming Language :: Python :: 3.8
Classifier: Programming Language :: Python :: 3 :: Only
Classifier: Topic :: Scientific/Engineering
Classifier: Topic :: Scientific/Engineering :: Mathematics
Classifier: Topic :: Scientific/Engineering :: Artificial Intelligence
Classifier: Topic :: Software Development
Classifier: Topic :: Software Development :: Libraries
Classifier: Topic :: Software Development :: Libraries :: Python Modules
Requires-Dist: torch (==1.7.0)
Requires-Dist: fsspec (==0.8.4)
Requires-Dist: pandas (==1.1.4)
Requires-Dist: tqdm (==4.54.0)
Requires-Dist: sklearn (==0.0)
Requires-Dist: absl-py (==0.11.0)
Requires-Dist: gcsfs (==0.7.1)
